setup.py
cadvisor_metrics.egg-info/PKG-INFO
cadvisor_metrics.egg-info/SOURCES.txt
cadvisor_metrics.egg-info/dependency_links.txt
cadvisor_metrics.egg-info/pbr.json
cadvisor_metrics.egg-info/requires.txt
cadvisor_metrics.egg-info/top_level.txt
collector/__init__.py
collector/collector.py
collector/example_collector.py