Metadata-Version: 1.0
Name: cadvisor-metrics
Version: 0.1.2
Summary: cAdvisor metrics collection from Docker containers running on multiple hosts.
Home-page: https://github.com/catalyzeio/cadvisor-metrics
Author: Ben Uphoff
Author-email: ben@catalyze.io
License: Apache 2.0
Keywords: docker cadvisor metrics container
Platform: UNKNOWN
